kmv/__init__.py
kmv/py.typed
kmv/app/__init__.py
kmv/app/viewer.py
kmv/core/__init__.py
kmv/core/controller.py
kmv/core/ring.py
kmv/core/streams.py
kmv/core/types.py
kmv/ipc/__init__.py
kmv/ipc/control.py
kmv/ipc/shared_ring.py
kmv/ui/__init__.py
kmv/ui/help.py
kmv/ui/plot.py
kmv/ui/settings.py
kmv/ui/table.py
kmv/ui/viewport.py
kmv/utils/__init__.py
kmv/utils/geometry.py
kmv/utils/logging.py
kmv/worker/__init__.py
kmv/worker/entrypoint.py
kmv/worker/window.py
mjviewer-0.3.23.dist-info/licenses/LICENSE
mjviewer-0.3.23.dist-info/METADATA
mjviewer-0.3.23.dist-info/WHEEL
mjviewer-0.3.23.dist-info/top_level.txt
mjviewer-0.3.23.dist-info/RECORD
