Metadata-Version: 2.4
Name: mjviewer
Version: 0.3.23
Summary: The mjviewer project, based on kscale-mujoco-viewer
Home-page: https://github.com/CCBR-Humanoid/mujoco-viewer
Author: Wesley Maa
Requires-Python: >=3.11
License-File: LICENSE
Requires-Dist: mujoco
Requires-Dist: PySide6==6.9.0
Requires-Dist: pyqtgraph
Requires-Dist: colorlogging
Provides-Extra: dev
Requires-Dist: black; extra == "dev"
Requires-Dist: darglint; extra == "dev"
Requires-Dist: mypy; extra == "dev"
Requires-Dist: pytest; extra == "dev"
Requires-Dist: ruff; extra == "dev"
Dynamic: author
Dynamic: description
Dynamic: description-content-type
Dynamic: home-page
Dynamic: license-file
Dynamic: provides-extra
Dynamic: requires-dist
Dynamic: requires-python
Dynamic: summary
